ka_uts_mail/__init__.py
ka_uts_mail/__version__.py
ka_uts_mail/do.py
ka_uts_mail/mail.py
ka_uts_mail/mailrcv.py
ka_uts_mail/mailsnd.py
ka_uts_mail/parms.py
ka_uts_mail/py.typed
ka_uts_mail/task.py
ka_uts_mail/ioc/jinja2_.py
ka_uts_mail/ioc/yaml_.py
ka_uts_mail-4.0.1.250513.dist-info/licenses/LICENSE.txt
ka_uts_mail-4.0.1.250513.dist-info/METADATA
ka_uts_mail-4.0.1.250513.dist-info/WHEEL
ka_uts_mail-4.0.1.250513.dist-info/entry_points.txt
ka_uts_mail-4.0.1.250513.dist-info/top_level.txt
ka_uts_mail-4.0.1.250513.dist-info/RECORD
