Metadata-Version: 2.4
Name: ka_uts_mail
Version: 4.0.1.250513
Summary: Email Utilities
Author-email: Bernd Stroehle <bernd.stroehle@gmail.com>
Maintainer-email: Bernd Stroehle <bernd.stroehle@gmail.com>
License-Expression: GPL-3.0-only WITH Classpath-exception-2.0 OR BSD-3-Clause
Project-URL: Source Code, https://github.com/bs29/ka_uts_mail/tree/master
Project-URL: Homepage, https://kosakya.de/
Project-URL: Documentation, https://ka-com.readthedocs.io/en/latest
Classifier: Development Status :: 5 - Production/Stable
Classifier: Intended Audience :: Developers
Classifier: Operating System :: OS Independent
Classifier: Programming Language :: Python :: 3.11
Classifier: Natural Language :: English
Classifier: Topic :: Software Development :: Libraries :: Python Modules
Requires-Python: >=3.10
License-File: LICENSE.txt
Requires-Dist: Jinja2>=3.1.6
Requires-Dist: ka_uts_aod>=4.0.1.250513
Requires-Dist: ka_uts_dic>=4.0.1.250513
Requires-Dist: ka_uts_log>=4.0.1.250513
Requires-Dist: ka_uts_obj>=4.0.1.250513
Requires-Dist: ka_uts_uts>=4.0.1.250513
Requires-Dist: msal>=1.32.3
Requires-Dist: PyYAML>=6.0.2
Dynamic: license-file
